libname/Moo.py
libname/__init__.py
annonymGenPro-0.0.13.dist-info/METADATA
annonymGenPro-0.0.13.dist-info/WHEEL
annonymGenPro-0.0.13.dist-info/top_level.txt
annonymGenPro-0.0.13.dist-info/RECORD
