Metadata-Version: 2.1
Name: annonymGenPro
Version: 0.0.13
Summary: A cool module for use
Home-page: UNKNOWN
Author: HushWatcher
Author-email: <thisismail@gmail.com>
License: UNKNOWN
Keywords: python,video,stream,video stream,camera stream,sockets
Platform: UNKNOWN
Classifier: Development Status :: 1 - Planning
Classifier: Intended Audience :: Developers
Classifier: Programming Language :: Python :: 3
Classifier: Operating System :: Unix
Classifier: Operating System :: MacOS :: MacOS X
Classifier: Operating System :: Microsoft :: Windows
